[
    {
        "title": "\u4eba\u5de5\u667a\u80fd\u4ea7\u54c1\u7ecf\u7406",
        "money": "15k-25k",
        "descs": "15k-25k",
        "wtime": "3-5\u5e74",
        "company": "\u8c37\u718a\u79d1\u6280",
        "ptime": "07\u670805\u65e5",
        "address": "\u6df1\u5733",
        "edu": "\u7855\u58eb"
    },
    {
        "title": "\u4eba\u5de5\u667a\u80fd",
        "money": "15k-30k",
        "descs": "15k-30k",
        "wtime": "3-5\u5e74",
        "company": "\u4eab\u5bb6\u4e50\u79d1\u6280",
        "ptime": "07\u670810\u65e5",
        "address": "\u6df1\u5733",
        "edu": "\u672c\u79d1"
    },
    {
        "title": "\u817e\u8baf\u91d1\u878dAI\u5e94\u7528-\u9ad8\u7ea7\u540e\u53f0\u5f00\u53d1\u5de5\u7a0b\u5e08",
        "money": "25k-50k",
        "descs": "25k-50k",
        "wtime": "3-5\u5e74",
        "company": "\u817e\u8baf",
        "ptime": "07\u670809\u65e5",
        "address": "\u6df1\u5733",
        "edu": "\u672c\u79d1"
    },
    {
        "title": "\u4eba\u5de5\u667a\u80fd\u5de5\u7a0b\u5e08",
        "money": "15k-20k",
        "descs": "15k-20k",
        "wtime": "1-3\u5e74",
        "company": "\u6df1\u5733\u7ea2\u5b69\u513f\u79d1\u6280",
        "ptime": "07\u670804\u65e5",
        "address": "\u6df1\u5733",
        "edu": "\u5927\u4e13"
    },
    {
        "title": "\u9ad8\u7ea7/\u9996\u5e2dAI\u8f6f\u4ef6\u5de5\u7a0b\u5e08\u548c\u79d1\u5b66\u5bb6",
        "money": "30k-60k",
        "descs": "30k-60k",
        "wtime": "3-5\u5e74",
        "company": "\u534e\u4e3a",
        "ptime": "07\u670806\u65e5",
        "address": "\u6df1\u5733",
        "edu": "\u672c\u79d1"
    },
    {
        "title": "AI\u673a\u5668\u5b66\u4e60\u4e13\u5bb6",
        "money": "25k-30k",
        "descs": "25k-30k",
        "wtime": "5-10\u5e74",
        "company": "\u534e\u4e3a\u6280\u672f\u6709\u9650\u516c\u53f8",
        "ptime": "07\u670806\u65e5",
        "address": "\u6df1\u5733",
        "edu": "\u672c\u79d1"
    },
    {
        "title": "AI\u8f6f\u4ef6\u5de5\u7a0b\u5e08",
        "money": "20k-40k",
        "descs": "20k-40k",
        "wtime": "1-3\u5e74",
        "company": "\u534e\u4e3a\u6280\u672f\u6709\u9650\u516c\u53f8",
        "ptime": "07\u670806\u65e5",
        "address": "\u6df1\u5733",
        "edu": "\u672c\u79d1"
    },
    {
        "title": "AI\u4ea7\u54c1\u7ecf\u7406",
        "money": "20k-25k",
        "descs": "20k-25k",
        "wtime": "5-10\u5e74",
        "company": "Webot",
        "ptime": "07\u670804\u65e5",
        "address": "\u6df1\u5733",
        "edu": "\u672c\u79d1"
    },
    {
        "title": "\u9ad8\u7ea7/\u9996\u5e2dAI\u8f6f\u4ef6\u5de5\u7a0b\u5e08\u548c\u79d1\u5b66\u5bb6",
        "money": "24k-40k",
        "descs": "24k-40k",
        "wtime": "1-3\u5e74",
        "company": "\u534e\u4e3a",
        "ptime": "07\u670806\u65e5",
        "address": "\u6df1\u5733",
        "edu": "\u672c\u79d1"
    },
    {
        "title": "AI\u667a\u80fd\u9500\u552e\u7ecf\u7406",
        "money": "5k-10k",
        "descs": "5k-10k",
        "wtime": "1-3\u5e74",
        "company": "\u7edf\u4e00\u901a\u4fe1",
        "ptime": "07\u670805\u65e5",
        "address": "\u6df1\u5733",
        "edu": "\u4e0d\u9650"
    },
    {
        "title": "\u4eba\u5de5\u667a\u80fdAI\u4e91\u4fa7\u5f00\u53d1\u5de5\u7a0b\u5e08",
        "money": "25k-50k",
        "descs": "25k-50k",
        "wtime": "3-5\u5e74",
        "company": "\u534e\u4e3a",
        "ptime": "07\u670803\u65e5",
        "address": "\u6df1\u5733",
        "edu": "\u7855\u58eb"
    },
    {
        "title": "\u4eba\u5de5\u667a\u80fd\u673a\u5668\u5b66\u4e60\u5de5\u7a0b\u5e08",
        "money": "20k-40k",
        "descs": "20k-40k",
        "wtime": "3-5\u5e74",
        "company": "\u987a\u4e30\u79d1\u6280",
        "ptime": "07\u670803\u65e5",
        "address": "\u6df1\u5733",
        "edu": "\u7855\u58eb"
    },
    {
        "title": "AI\u540e\u53f0\u5f00\u53d1",
        "money": "17k-34k",
        "descs": "17k-34k",
        "wtime": "3-5\u5e74",
        "company": "\u817e\u8baf",
        "ptime": "07\u670804\u65e5",
        "address": "\u6df1\u5733",
        "edu": "\u672c\u79d1"
    },
    {
        "title": "\u4eba\u5de5\u667a\u80fd-\u79d1\u5b66\u5bb6",
        "money": "36k-60k",
        "descs": "36k-60k",
        "wtime": "5-10\u5e74",
        "company": "\u534e\u4e3a\u6280\u672f\u6709\u9650\u516c\u53f8",
        "ptime": "07\u670805\u65e5",
        "address": "\u6df1\u5733",
        "edu": "\u535a\u58eb"
    },
    {
        "title": "\u6570\u636e\u5f00\u53d1\uff08\u5927\u6570\u636e\uff0c\u4e91\u5e73\u53f0\uff0cAI\uff0c\u533a\u5757\u94fe\uff09",
        "money": "16k-31k",
        "descs": "16k-31k",
        "wtime": "1-3\u5e74",
        "company": "\u8f6f\u901a\u52a8\u529b",
        "ptime": "07\u670804\u65e5",
        "address": "\u6df1\u5733",
        "edu": "\u5927\u4e13"
    },
    {
        "title": "AI\u56e2\u961f\u4eba\u5de5\u5e72\u9884\u5c97",
        "money": "5k-6k",
        "descs": "5k-6k",
        "wtime": "1\u5e74\u4ee5\u5185",
        "company": "\u4ebf\u8d77\u878d\u7f51\u7edc\u79d1\u6280",
        "ptime": "06\u670826\u65e5",
        "address": "\u6df1\u5733",
        "edu": "\u5927\u4e13"
    },
    {
        "title": "AI/\u5927\u6570\u636e/\u7b97\u6cd5/\u8ba1\u7b97\u5e7f\u544a",
        "money": "30k-60k",
        "descs": "30k-60k",
        "wtime": "\u4e0d\u9650",
        "company": "\u817e\u8baf",
        "ptime": "07\u670804\u65e5",
        "address": "\u6df1\u5733",
        "edu": "\u7855\u58eb"
    },
    {
        "title": "AI\u5927\u6570\u636e\u540e\u53f0\u5f00\u53d1\u5de5\u7a0b\u5e08",
        "money": "15k-30k",
        "descs": "15k-30k",
        "wtime": "3-5\u5e74",
        "company": "\u817e\u8baf",
        "ptime": "07\u670803\u65e5",
        "address": "\u6df1\u5733",
        "edu": "\u672c\u79d1"
    },
    {
        "title": "Python\u5de5\u7a0b\u5e08\uff08\u4eba\u5de5\u667a\u80fd\u65b9\u5411\uff09",
        "money": "8k-16k",
        "descs": "8k-16k",
        "wtime": "\u4e0d\u9650",
        "company": "\u8d1d\u5c14\u4fe1\u606f",
        "ptime": "05\u670817\u65e5",
        "address": "\u6df1\u5733",
        "edu": "\u672c\u79d1"
    },
    {
        "title": "AI\u5927\u6570\u636e\u540e\u53f0\u5f00\u53d1\u5de5\u7a0b\u5e08",
        "money": "18k-36k",
        "descs": "18k-36k",
        "wtime": "3-5\u5e74",
        "company": "\u817e\u8baf",
        "ptime": "07\u670802\u65e5",
        "address": "\u6df1\u5733",
        "edu": "\u672c\u79d1"
    },
    {
        "title": "AI\u7b97\u6cd5\u5de5\u7a0b\u5e08\u5c97\u4f4d",
        "money": "20k-40k",
        "descs": "20k-40k",
        "wtime": "\u4e0d\u9650",
        "company": "\u534e\u4e3a\u6280\u672f\u6709\u9650\u516c\u53f8",
        "ptime": "06\u670830\u65e5",
        "address": "\u6df1\u5733",
        "edu": "\u672c\u79d1"
    },
    {
        "title": "AI\u5de5\u7a0b\u5e08",
        "money": "15k-25k",
        "descs": "15k-25k",
        "wtime": "\u4e0d\u9650",
        "company": "\u8054\u8f6f\u79d1\u6280",
        "ptime": "07\u670804\u65e5",
        "address": "\u6df1\u5733",
        "edu": "\u7855\u58eb"
    },
    {
        "title": "AI\u8bad\u7ec3\u5e08",
        "money": "4k-7k",
        "descs": "4k-7k",
        "wtime": "\u4e0d\u9650",
        "company": "\u4eba\u9a6c\u4e92\u52a8",
        "ptime": "06\u670829\u65e5",
        "address": "\u6df1\u5733",
        "edu": "\u5927\u4e13"
    },
    {
        "title": "AI\u9ad8\u7ea7\u4ea7\u54c1\u7ecf\u7406-\u673a\u5668\u5b66\u4e60/NLP\u65b9\u5411",
        "money": "15k-25k",
        "descs": "15k-25k",
        "wtime": "5-10\u5e74",
        "company": "\u5b89\u6c38(\u4e2d\u56fd)\u4f01\u4e1a\u8c18\u8be2",
        "ptime": "07\u670801\u65e5",
        "address": "\u6df1\u5733",
        "edu": "\u7855\u58eb"
    },
    {
        "title": "\u4eba\u5de5\u667a\u80fd\u9500\u552e\u4e13\u5458",
        "money": "4k-8k",
        "descs": "4k-8k",
        "wtime": "1-3\u5e74",
        "company": "\u6709\u7535\u7269\u8054",
        "ptime": "06\u670821\u65e5",
        "address": "\u6df1\u5733",
        "edu": "\u5927\u4e13"
    },
    {
        "title": "\u548c\u800c\u6cf0 419 Lab \u4eba\u5de5\u667a\u80fd\u4ea7\u54c1\u7ecf\u7406",
        "money": "15k-30k",
        "descs": "15k-30k",
        "wtime": "3-5\u5e74",
        "company": "\u548c\u800c\u6cf0",
        "ptime": "07\u670805\u65e5",
        "address": "\u6df1\u5733",
        "edu": "\u672c\u79d1"
    },
    {
        "title": "\u4e92\u8054\u7f51\u4ea7\u54c1\u7ecf\u7406\uff08AI\u667a\u80fd\u670d\u52a1\uff09",
        "money": "25k-50k",
        "descs": "25k-50k",
        "wtime": "5-10\u5e74",
        "company": "\u5e73\u5b89\u94f6\u884c",
        "ptime": "06\u670828\u65e5",
        "address": "\u6df1\u5733",
        "edu": "\u672c\u79d1"
    },
    {
        "title": "\u4eba\u5de5\u667a\u80fd\u7b97\u6cd5\u5de5\u7a0b\u5e08",
        "money": "12k-24k",
        "descs": "12k-24k",
        "wtime": "1-3\u5e74",
        "company": "\u5143\u5f81\u79d1\u6280",
        "ptime": "06\u670826\u65e5",
        "address": "\u6df1\u5733",
        "edu": "\u672c\u79d1"
    },
    {
        "title": "AI\u8bad\u7ec3\u5e08",
        "money": "4k-7k",
        "descs": "4k-7k",
        "wtime": "1-3\u5e74",
        "company": "\u4eba\u9a6c\u4e92\u52a8",
        "ptime": "06\u670822\u65e5",
        "address": "\u6df1\u5733",
        "edu": "\u672c\u79d1"
    },
    {
        "title": "\u4eba\u5de5\u667a\u80fd\u8bfe\u7a0b\u8bb2\u5e08",
        "money": "4k-8k",
        "descs": "4k-8k",
        "wtime": "\u4e0d\u9650",
        "company": "\u593a\u84dd\u7f51\u7edc",
        "ptime": "07\u670806\u65e5",
        "address": "\u6df1\u5733",
        "edu": "\u4e0d\u9650"
    }
]